pre_commit_hook_ensure_sops/__init__.py
pre_commit_hook_ensure_sops/__main__.py
pre_commit_hook_ensure_sops-1.1.dist-info/LICENSE
pre_commit_hook_ensure_sops-1.1.dist-info/METADATA
pre_commit_hook_ensure_sops-1.1.dist-info/WHEEL
pre_commit_hook_ensure_sops-1.1.dist-info/top_level.txt
pre_commit_hook_ensure_sops-1.1.dist-info/RECORD
