Metadata-Version: 2.1
Name: pre-commit-hook-ensure-sops
Version: 1.1
Summary: pre-commit hook to ensure that files that should be encrypted with sops are in fact encrypted
Home-page: https://github.com/yuvipanda/pre-commit-hook-ensure-sops
Author: Yuvi Panda
Author-email: yuvipanda@gmail.com
License-File: LICENSE
Requires-Dist: ruamel.yaml
